[
  {
    "key": "favourites.add.post",
    "path": "/blogs/{BLOG_ID}/favourite/add/post",
    "permissions": [],
    "controller": "\\HamletCMS\\FavouriteBlogs\\Controller\\Favourites",
    "action": "addPostToFavourites"
  },
  {
    "key": "favourites.remove.post",
    "path": "/blogs/{BLOG_ID}/favourite/remove/post",
    "permissions": [],
    "controller": "\\HamletCMS\\FavouriteBlogs\\Controller\\Favourites",
    "action": "removePostFromFavourites"
  },
  {
    "key": "favourites.add.blog",
    "path": "/blogs/{BLOG_ID}/favourite/add",
    "permissions": [],
    "controller": "\\HamletCMS\\FavouriteBlogs\\Controller\\Favourites",
    "action": "addBlogToFavourites"
  },
  {
    "key": "favourites.remove.blog",
    "path": "/blogs/{BLOG_ID}/favourite/remove",
    "permissions": [],
    "controller": "\\HamletCMS\\FavouriteBlogs\\Controller\\Favourites",
    "action": "removeBlogFromFavourites"
  },
  {
    "key": "favourites.view",
    "path": "/cms/my-favourites",
    "permissions": [],
    "controller": "\\HamletCMS\\FavouriteBlogs\\Controller\\Favourites",
    "action": "viewFavourites"
  }
]